syna/__init__.py
syna/algo/__init__.py
syna/algo/dqn.py
syna/core.py
syna/datasets/__init__.py
syna/datasets/datasets.py
syna/functions/__init__.py
syna/functions/activation.py
syna/functions/function.py
syna/functions/loss.py
syna/functions/math.py
syna/layers/__init__.py
syna/layers/layer.py
syna/layers/rnn.py
syna/models/__init__.py
syna/models/models.py
syna/optim/__init__.py
syna/optim/adadelta.py
syna/optim/adagrad.py
syna/optim/adam.py
syna/optim/optimizer.py
syna/optim/sgd.py
syna/utils/__init__.py
syna/utils/dataloaders.py
syna/utils/rl.py
syna/utils/transforms.py
syna/utils/util.py
syna/utils/viz.py
syna-0.3.0.dist-info/WHEEL
syna-0.3.0.dist-info/METADATA
syna-0.3.0.dist-info/RECORD
