Metadata-Version: 2.3
Name: syna
Version: 0.3.0
Summary: Syna is a lightweight machine learning framework inspired by DeZero.
Author: sql-hkr
Author-email: sql-hkr <sql.hkr@gmail.com>
Classifier: License :: OSI Approved :: MIT License
Classifier: Programming Language :: Python :: 3.11
Classifier: Programming Language :: Python :: 3.12
Classifier: Programming Language :: Python :: 3.13
Requires-Dist: gymnasium[classic-control]>=1.2.1
Requires-Dist: matplotlib>=3.10.6
Requires-Dist: numpy>=2.2.6
Requires-Python: >=3.11
